wagtail_admin_preview/__init__.py
wagtail_admin_preview/apps.py
wagtail_admin_preview/panels.py
wagtail_admin_preview/wagtail_hooks.py
wagtail_admin_preview/migrations/__init__.py
wagtail_admin_preview/templates/wagtail_admin_preview/preview_panel.html
wagtail_admin_preview/templates/wagtailadmin/icons/desktop-screen.svg
wagtail_admin_preview/templates/wagtailadmin/icons/mobile-screen.svg
wagtail_admin_preview/templates/wagtailadmin/icons/tablet-screen.svg
wagtail_admin_preview-0.1.0.dist-info/LICENSE
wagtail_admin_preview-0.1.0.dist-info/METADATA
wagtail_admin_preview-0.1.0.dist-info/WHEEL
wagtail_admin_preview-0.1.0.dist-info/top_level.txt
wagtail_admin_preview-0.1.0.dist-info/RECORD
