Metadata-Version: 2.1
Name: wagtail-admin-preview
Version: 0.1.0
Summary: Simple Page Preview Tab in Wagtail Admin Panel
Home-page: https://github.com/sadat-sakif-ahmed/wagtail-admin-preview
Author: Sadat Sakif Ahmed
Author-email: sadat_s_ahmed@outlook.com
Maintainer: Sadat Sakif Ahmed
Maintainer-email: sadat_s_ahmed@outlook.com
License: BSD
Keywords: django,wagtail,wagtail-cms,admin-preview
Platform: UNKNOWN
Classifier: Framework :: Wagtail
Classifier: Framework :: Django
Classifier: Programming Language :: Python
Classifier: Programming Language :: Python :: 3
Classifier: Environment :: Web Environment
Classifier: Intended Audience :: Developers
Classifier: License :: OSI Approved :: BSD License
Classifier: Operating System :: OS Independent
Classifier: Topic :: Internet :: WWW/HTTP :: Site Management
License-File: LICENSE
Requires-Dist: wagtail (>=3.0)
